rocketmq/client.py
rocketmq/client_config.py
rocketmq/client_id_encoder.py
rocketmq/client_manager.py
rocketmq/consumer.py
rocketmq/definition.py
rocketmq/exponential_backoff_retry_policy.py
rocketmq/filter_expression.py
rocketmq/foo.py
rocketmq/log.py
rocketmq/message.py
rocketmq/message_id.py
rocketmq/message_id_codec.py
rocketmq/producer.py
rocketmq/protocol/__init__.py
rocketmq/protocol/admin_pb2.py
rocketmq/protocol/admin_pb2.pyi
rocketmq/protocol/admin_pb2_grpc.py
rocketmq/protocol/definition_pb2.py
rocketmq/protocol/definition_pb2.pyi
rocketmq/protocol/definition_pb2_grpc.py
rocketmq/protocol/service_pb2.py
rocketmq/protocol/service_pb2.pyi
rocketmq/protocol/service_pb2_grpc.py
rocketmq/publish_settings.py
rocketmq/publishing_message.py
rocketmq/rpc_client.py
rocketmq/send_receipt.py
rocketmq/session.py
rocketmq/session_credentials.py
rocketmq/settings.py
rocketmq/signature.py
rocketmq/simple_consumer.py
rocketmq/simple_subscription_settings.py
rocketmq/state.py
rocketmq/status_checker.py
rocketmq/utils.py
rocketmq_yue-0.1.0.dist-info/METADATA
rocketmq_yue-0.1.0.dist-info/WHEEL
rocketmq_yue-0.1.0.dist-info/RECORD
